pyrua/__init__.py
pyrua/py.typed
pyrua/pyrua.py
pyrua-1.0.0.dist-info/licenses/LICENSE
pyrua-1.0.0.dist-info/METADATA
pyrua-1.0.0.dist-info/WHEEL
pyrua-1.0.0.dist-info/top_level.txt
pyrua-1.0.0.dist-info/RECORD
