Metadata-Version: 2.4
Name: pyrua
Version: 1.0.0
Summary: Professional Random User-Agent Generator for web scraping and browser simulation
Home-page: https://github.com/farhaanaliii/pyrua
Author: Farhan Ali
Author-email: Farhan Ali <i.farhanali.dev@gmail.com>
Maintainer-email: Farhan Ali <i.farhanali.dev@gmail.com>
License: MIT
Project-URL: Homepage, https://github.com/farhaanaliii/pyrua
Project-URL: Documentation, https://github.com/farhaanaliii/pyrua#readme
Project-URL: Repository, https://github.com/farhaanaliii/pyrua.git
Project-URL: Issues, https://github.com/farhaanaliii/pyrua/issues
Project-URL: Changelog, https://github.com/farhaanaliii/pyrua/blob/main/CHANGELOG.md
Keywords: pyrua,user-agent,useragent,random-user-agent,web-scraping,browser-simulation,http-headers,web-crawler,scraping,automation,testing,chrome,firefox,safari,edge
Classifier: Development Status :: 5 - Production/Stable
Classifier: Intended Audience :: Developers
Classifier: License :: OSI Approved :: MIT License
Classifier: Operating System :: OS Independent
Classifier: Programming Language :: Python :: 3
Classifier: Programming Language :: Python :: 3.8
Classifier: Programming Language :: Python :: 3.9
Classifier: Programming Language :: Python :: 3.10
Classifier: Programming Language :: Python :: 3.11
Classifier: Programming Language :: Python :: 3.12
Classifier: Topic :: Internet :: WWW/HTTP
Classifier: Topic :: Software Development :: Libraries :: Python Modules
Classifier: Topic :: Software Development :: Testing
Classifier: Typing :: Typed
Requires-Python: >=3.8
License-File: LICENSE
Dynamic: author
Dynamic: home-page
Dynamic: license-file
Dynamic: requires-python
